ontologyclient/__init__.py
ontologyclient/enum.py
ontologyclient/openapi_client/__init__.py
ontologyclient/openapi_client/api/__init__.py
ontologyclient/openapi_client/api/default_api.py
ontologyclient/openapi_client/api_client.py
ontologyclient/openapi_client/api_response.py
ontologyclient/openapi_client/configuration.py
ontologyclient/openapi_client/exceptions.py
ontologyclient/openapi_client/models/__init__.py
ontologyclient/openapi_client/models/http_validation_error.py
ontologyclient/openapi_client/models/validation_error.py
ontologyclient/openapi_client/models/validation_error_loc_inner.py
ontologyclient/openapi_client/py.typed
ontologyclient/openapi_client/rest.py
test321421-0.1.2.dist-info/METADATA
test321421-0.1.2.dist-info/WHEEL
test321421-0.1.2.dist-info/RECORD
