Metadata-Version: 2.3
Name: test321421
Version: 0.1.2
Summary: 
Author: Jason Koh
Author-email: jason@mapped.com
Requires-Python: >=3.10,<4.0
Classifier: Programming Language :: Python :: 3
Classifier: Programming Language :: Python :: 3.10
Classifier: Programming Language :: Python :: 3.11
Classifier: Programming Language :: Python :: 3.12
Classifier: Programming Language :: Python :: 3.13
Requires-Dist: fastapi[standard] (>=0.116.2,<0.117.0)
Requires-Dist: pydantic (>=2.11.9,<3.0.0)
Requires-Dist: python-dateutil (>=2.9.0.post0,<3.0.0)
Requires-Dist: typing-extensions (>=4.15.0,<5.0.0)
Requires-Dist: urllib3 (>=2.5.0,<3.0.0)
